LICENSE
README.rst
python-cicoclient.spec
requirements.txt
setup.cfg
setup.py
test-requirements.txt
tox.ini
.github/workflows/main.yml
cicoclient/__init__.py
cicoclient/cli.py
cicoclient/client.py
cicoclient/exceptions.py
cicoclient/shell.py
cicoclient/utils.py
cicoclient/wrapper.py
cicoclient/ansible/ansible.cfg.example
cicoclient/ansible/cico.py
docs/Makefile
docs/ansible_usage.rst
docs/cli_usage.rst
docs/conf.py
docs/index.rst
docs/installing.rst
python_cicoclient.egg-info/PKG-INFO
python_cicoclient.egg-info/SOURCES.txt
python_cicoclient.egg-info/dependency_links.txt
python_cicoclient.egg-info/entry_points.txt
python_cicoclient.egg-info/not-zip-safe
python_cicoclient.egg-info/pbr.json
python_cicoclient.egg-info/requires.txt
python_cicoclient.egg-info/top_level.txt