Metadata-Version: 2.1
Name: python-cicoclient
Version: 0.4.7
Summary: A client library for the ci.centos.org administrative interface
Home-page: https://github.com/dmsimard/python-cicoclient
Author: David Moreau Simard
Author-email: dms@redhat.com
License: UNKNOWN
Platform: UNKNOWN
Classifier: License :: OSI Approved :: Apache Software License
Classifier: Development Status :: 4 - Beta
Classifier: Intended Audience :: Developers
Classifier: Intended Audience :: System Administrators
Classifier: Intended Audience :: Information Technology
Classifier: Programming Language :: Python :: 2.7
Classifier: Topic :: Utilities
License-File: LICENSE
